django_geonode_mapstore_client-5.0.0.dist-info/licenses/AUTHORS
django_geonode_mapstore_client-5.0.0.dist-info/licenses/LICENSE
geonode_mapstore_client/__init__.py
geonode_mapstore_client/admin.py
geonode_mapstore_client/apps.py
geonode_mapstore_client/context_processors.py
geonode_mapstore_client/hooksets.py
geonode_mapstore_client/models.py
geonode_mapstore_client/tests.py
geonode_mapstore_client/utils.py
geonode_mapstore_client/views.py
geonode_mapstore_client/migrations/0001_clean_prev_version_geoapps.py
geonode_mapstore_client/migrations/0002_migrate_map_blob.py
geonode_mapstore_client/migrations/0003_searchservice.py
geonode_mapstore_client/migrations/0004_auto_20231114_1705.py
geonode_mapstore_client/migrations/0005_extension.py
geonode_mapstore_client/migrations/0006_searchservice_namefield.py
geonode_mapstore_client/migrations/0007_searchservice_sub_title_and_more.py
geonode_mapstore_client/migrations/__init__.py
geonode_mapstore_client/static/admin/css/theme.css
geonode_mapstore_client/static/fonts/montserrat-v25-latin-300.woff
geonode_mapstore_client/static/fonts/montserrat-v25-latin-300.woff2
geonode_mapstore_client/static/fonts/montserrat-v25-latin-300italic.woff
geonode_mapstore_client/static/fonts/montserrat-v25-latin-300italic.woff2
geonode_mapstore_client/static/fonts/montserrat-v25-latin-700.woff
geonode_mapstore_client/static/fonts/montserrat-v25-latin-700.woff2
geonode_mapstore_client/static/fonts/montserrat-v25-latin-700italic.woff
geonode_mapstore_client/static/fonts/montserrat-v25-latin-700italic.woff2
geonode_mapstore_client/static/fonts/montserrat-v25-latin-italic.woff
geonode_mapstore_client/static/fonts/montserrat-v25-latin-italic.woff2
geonode_mapstore_client/static/fonts/montserrat-v25-latin-regular.woff
geonode_mapstore_client/static/fonts/montserrat-v25-latin-regular.woff2
geonode_mapstore_client/static/fonts/montserrat.css
geonode_mapstore_client/static/mapstore/README.md
geonode_mapstore_client/static/mapstore/version.txt
geonode_mapstore_client/static/mapstore/configs/geostory.json
geonode_mapstore_client/static/mapstore/configs/localConfig.json
django_geonode_mapstore_client-5.0.0.dist-info/METADATA
django_geonode_mapstore_client-5.0.0.dist-info/WHEEL
django_geonode_mapstore_client-5.0.0.dist-info/top_level.txt
django_geonode_mapstore_client-5.0.0.dist-info/RECORD
