Metadata-Version: 2.4
Name: django-geonode-mapstore-client
Version: 5.0.0
Summary: Use GeoNode client in your django projects
Home-page: https://github.com/GeoNode/geonode-mapstore-client
Download-URL: https://github.com/GeoNode/geonode-mapstore-client/tarball/master
Author: Alessio Fabiani
Author-email: alessio.fabiani@geo-solutions.it
Keywords: django,mapstore,mapstore2
Classifier: Development Status :: 5 - Production/Stable
Classifier: Environment :: Web Environment
Classifier: Framework :: Django
Classifier: Intended Audience :: Developers
Classifier: License :: OSI Approved :: BSD License
Classifier: Operating System :: OS Independent
Classifier: Topic :: Internet :: WWW/HTTP
Classifier: Programming Language :: Python :: 3.7
License-File: LICENSE
License-File: AUTHORS
Requires-Dist: django<5.3,>=4.2
Requires-Dist: idna<2.11,>=2.5
Requires-Dist: requests>=2.13.0
Requires-Dist: Markdown>=2.6.11
Requires-Dist: MarkupSafe>=1.1.1
Requires-Dist: urllib3>=1.25
Dynamic: description
Dynamic: description-content-type
Dynamic: download-url
Dynamic: license-file
